shop/BinaryTree.py
shop/Filter.py
shop/Infix_to_Polish.py
shop/Parsers.py
shop/Query.py
shop/Record.py
shop/Shop.py
shop/__init__.py
Shop_Filtering_Tool_Inect_1-0.0.1.dist-info/LICENSE.txt
Shop_Filtering_Tool_Inect_1-0.0.1.dist-info/METADATA
Shop_Filtering_Tool_Inect_1-0.0.1.dist-info/WHEEL
Shop_Filtering_Tool_Inect_1-0.0.1.dist-info/top_level.txt
Shop_Filtering_Tool_Inect_1-0.0.1.dist-info/RECORD
